matrix_completion/__init__.py
matrix_completion/bias_solver.py
matrix_completion/evaluation.py
matrix_completion/nuc_solver.py
matrix_completion/pmf_solver.py
matrix_completion/svt_solver.py
matrix_completion/synthesize_data.py
matrix_completion-0.0.2.dist-info/LICENSE
matrix_completion-0.0.2.dist-info/METADATA
matrix_completion-0.0.2.dist-info/WHEEL
matrix_completion-0.0.2.dist-info/top_level.txt
matrix_completion-0.0.2.dist-info/RECORD
