Metadata-Version: 2.1
Name: matrix-completion
Version: 0.0.2
Summary: Python code for a few approaches at matrix completion.
Home-page: https://github.com/tonyduan/matrix-completion
Author: Tony Duan
Author-email: tonyduan@cs.stanford.edu
License: UNKNOWN
Platform: UNKNOWN
Classifier: Programming Language :: Python :: 3
Classifier: License :: OSI Approved :: Eclipse Public License 2.0 (EPL-2.0)
Classifier: Operating System :: OS Independent
